{
  "globals": {
    "IconPhArrowCounterClockwise": true,
    "IconPhBooks": true,
    "IconPhBuildings": true,
    "IconPhCaretDown": true,
    "IconPhCirclesThree": true,
    "IconPhFiles": true,
    "IconPhGraduationCap": true,
    "IconPhHandshake": true,
    "IconPhHouse": true,
    "IconPhList": true,
    "IconPhMegaphone": true,
    "IconPhMoonStars": true,
    "IconPhPencilSimple": true,
    "IconPhPlus": true,
    "IconPhSortAscending": true,
    "IconPhSortDescending": true,
    "IconPhStudent": true,
    "IconPhSun": true,
    "IconPhTicket": true,
    "IconPhUser": true,
    "IconPhUsers": true,
    "IconPhWarningCircle": true,
    "IconPhX": true,
    "IconPhXCircle": true
  }
}